libface/__init__.py
libface/base.py
libface/datastruct.py
libface/downloader.py
libface/logger.py
libface/transforms.py
libface/utils.py
libface/analyzer/__init__.py
libface/analyzer/core.py
libface/analyzer/detector/__init__.py
libface/analyzer/detector/core.py
libface/analyzer/detector/post.py
libface/analyzer/detector/pre.py
libface/analyzer/predictor/__init__.py
libface/analyzer/predictor/core.py
libface/analyzer/predictor/post.py
libface/analyzer/predictor/pre.py
libface/analyzer/reader/__init__.py
libface/analyzer/reader/core.py
libface/analyzer/unifier/__init__.py
libface/analyzer/unifier/core.py
libface/analyzer/utilizer/__init__.py
libface/analyzer/utilizer/align.py
libface/analyzer/utilizer/draw.py
libface/analyzer/utilizer/save.py
libface-0.1.2.dist-info/LICENSE
libface-0.1.2.dist-info/METADATA
libface-0.1.2.dist-info/WHEEL
libface-0.1.2.dist-info/top_level.txt
libface-0.1.2.dist-info/RECORD
