Metadata-Version: 2.1
Name: libface
Version: 0.1.2
Summary: Face analysis library.
Home-page: https://github.com/li-yibing/libface
Download-URL: https://pypi.org/project/libface/
Author: li-yibing
Author-email: li_yi_bing@outlook.com
Maintainer: li-yibing
Maintainer-email: li_yi_bing@outlook.com
Classifier: Development Status :: 3 - Alpha
Classifier: Environment :: Console
Classifier: Intended Audience :: Science/Research
Classifier: Intended Audience :: End Users/Desktop
Classifier: License :: OSI Approved :: Apache Software License
Classifier: Natural Language :: English
Classifier: Operating System :: OS Independent
Classifier: Programming Language :: Python :: 3
Classifier: Programming Language :: Python :: 3.8
Classifier: Programming Language :: Python :: 3.9
Classifier: Programming Language :: Python :: 3.10
Classifier: Topic :: Scientific/Engineering :: Artificial Intelligence
Classifier: Topic :: Software Development :: Libraries :: Python Modules
Requires-Python: >=3.8
License-File: LICENSE
Requires-Dist: googleapis-common-protos >=1.56.3
Requires-Dist: gdown >=3.11.0
Requires-Dist: hydra-core >=1.0.0
Requires-Dist: numpy >=1.18.2
Requires-Dist: pip >=20.0.2
Requires-Dist: python-json-logger >=2.0.0
Requires-Dist: torch >=1.9.0
Requires-Dist: torchvision >=0.10.0
